sqltrie/__init__.py
sqltrie/py.typed
sqltrie/pygtrie.py
sqltrie/serialized.py
sqltrie/sqlalchemy.py
sqltrie/trie.py
sqltrie/__pyinstaller/__init__.py
sqltrie/__pyinstaller/hook-sqltrie.py
sqltrie/__pyinstaller/test_hook-sqltrie.py
sqltrie/sqlite/__init__.py
sqltrie/sqlite/diff.sql
sqltrie/sqlite/init.sql
sqltrie/sqlite/sqlite.py
sqltrie/sqlite/steps.sql
sqltrie-0.11.1.dist-info/LICENSE
sqltrie-0.11.1.dist-info/METADATA
sqltrie-0.11.1.dist-info/WHEEL
sqltrie-0.11.1.dist-info/entry_points.txt
sqltrie-0.11.1.dist-info/top_level.txt
sqltrie-0.11.1.dist-info/RECORD
