Metadata-Version: 2.1
Name: sqltrie
Version: 0.11.1
Summary: SQL-based prefix tree inspired by pygtrie and python-diskcache
Author-email: Ruslan Kuprieiev <ruslan@iterative.ai>
License: Apache-2.0
Project-URL: Issues, https://github.com/efiop/sqltrie/issues
Project-URL: Source, https://github.com/efiop/sqltrie
Classifier: Programming Language :: Python :: 3
Classifier: Programming Language :: Python :: 3.9
Classifier: Programming Language :: Python :: 3.10
Classifier: Programming Language :: Python :: 3.11
Classifier: Programming Language :: Python :: 3.12
Classifier: Development Status :: 1 - Planning
Requires-Python: >=3.8
License-File: LICENSE
Requires-Dist: attrs>=22.2.0
Requires-Dist: orjson; implementation_name == "cpython"
Requires-Dist: pygtrie
Provides-Extra: tests
Requires-Dist: pytest==7.2.0; extra == "tests"
Requires-Dist: pytest-sugar==0.9.5; extra == "tests"
Requires-Dist: pytest-cov==3.0.0; extra == "tests"
Requires-Dist: pytest-mock==3.8.2; extra == "tests"
Requires-Dist: mypy==0.971; extra == "tests"
Requires-Dist: pytest-benchmark; extra == "tests"
Requires-Dist: pyinstaller; extra == "tests"
Provides-Extra: dev
Requires-Dist: sqltrie[tests]; extra == "dev"
